budge/__init__.py
budge/account.py
budge/collection.py
budge/date.py
budge/money.py
budge/py.typed
budge/rrule.py
budge/transaction.py
budge/transfer.py
budge-1.2.0.dist-info/METADATA
budge-1.2.0.dist-info/WHEEL
budge-1.2.0.dist-info/licenses/LICENSE-GPL.md
budge-1.2.0.dist-info/licenses/LICENSE.md
budge-1.2.0.dist-info/RECORD
