Metadata-Version: 2.4
Name: budge
Version: 1.2.0
Summary: Track your budgets and forecast your balances with Python.
Project-URL: Repository, https://github.com/budgeapp/budge
Project-URL: Documentation, https://budge.readthedocs.io/en/stable/
Author-email: Jesse Brooklyn Hannah <jesse@jbhannah.net>
License-File: LICENSE-GPL.md
License-File: LICENSE.md
Classifier: Development Status :: 5 - Production/Stable
Classifier: License :: OSI Approved :: GNU Lesser General Public License v3 or later (LGPLv3+)
Classifier: Programming Language :: Python :: 3.13
Classifier: Programming Language :: Python :: 3.14
Classifier: Topic :: Office/Business :: Financial :: Accounting
Classifier: Topic :: Software Development :: Libraries :: Python Modules
Classifier: Typing :: Typed
Requires-Python: ~=3.13
Requires-Dist: python-dateutil~=2.9.0
Requires-Dist: stockholm~=0.5.7
